ptk_blinkfix/__init__.py
ptk_blinkfix/blink_fix.py
ptk_blinkfix-1.0.1.dist-info/licenses/LICENSE
ptk_blinkfix-1.0.1.dist-info/METADATA
ptk_blinkfix-1.0.1.dist-info/WHEEL
ptk_blinkfix-1.0.1.dist-info/top_level.txt
ptk_blinkfix-1.0.1.dist-info/RECORD
