Metadata-Version: 2.4
Name: ptk-blinkfix
Version: 1.0.1
Summary: Blinking cursor fix for Python prompt_toolkit apps
Home-page: https://github.com/ahmetaltin/ptk-blinkfix
Author: Ahmet Altin
Author-email: Ahmet Altin <me@ahmetaltin.com>
Maintainer-email: Ahmet Altin <me@ahmetaltin.com>
License: BSD 3-Clause License
Project-URL: Homepage, https://github.com/ahmetaltin/ptk-blinkfix
Project-URL: Repository, https://github.com/ahmetaltin/ptk-blinkfix
Project-URL: Issues, https://github.com/ahmetaltin/ptk-blinkfix/issues
Keywords: prompt_toolkit,cursor,blinking,terminal,cli
Classifier: License :: OSI Approved :: BSD License
Classifier: Programming Language :: Python :: 3
Classifier: Programming Language :: Python :: 3.8
Classifier: Programming Language :: Python :: 3.9
Classifier: Programming Language :: Python :: 3.10
Classifier: Programming Language :: Python :: 3.11
Classifier: Programming Language :: Python :: 3.12
Classifier: Operating System :: OS Independent
Requires-Python: >=3.7
License-File: LICENSE
Requires-Dist: prompt_toolkit>=3.0.0
Dynamic: author
Dynamic: home-page
Dynamic: license-file
Dynamic: requires-python
